dooers/cli.py
dooers-0.2.1.dist-info/METADATA
dooers-0.2.1.dist-info/WHEEL
dooers-0.2.1.dist-info/entry_points.txt
dooers-0.2.1.dist-info/top_level.txt
dooers-0.2.1.dist-info/RECORD
