Metadata-Version: 2.4
Name: dooers
Version: 0.2.1
Summary: Dooers CLI: push agents with .dooersignore, dynamic routing, and progress spinner
Author-email: Dooers <dev@dooers.example>
License: MIT
Keywords: cli,deployment,agents,docker,gcp
Classifier: Development Status :: 4 - Beta
Classifier: Intended Audience :: Developers
Classifier: License :: OSI Approved :: MIT License
Classifier: Programming Language :: Python :: 3
Classifier: Programming Language :: Python :: 3.9
Classifier: Programming Language :: Python :: 3.10
Classifier: Programming Language :: Python :: 3.11
Classifier: Programming Language :: Python :: 3.12
Requires-Python: >=3.9
Requires-Dist: typer>=0.12.3
Requires-Dist: requests>=2.32.3
Requires-Dist: tqdm>=4.66.4
